<?xml version="1.0" encoding="utf-8" ?>

<tree>
    <branch title="Головна" alias="" controller="Home" menu="Головна" />
    <branch title="Публікації" alias="публікації" controller="Publication">
        <branch title="Список" alias="список" controller="Index" menu="Публікації">
            <submenu>
                <item title="Створити" alias="редагування" />
                <item title="Фільтр" alias="фільтр" />
            </submenu>
        </branch>
        <branch title="Перегляд" alias="перегляд" controller="View" />
        <branch title="Редагування" alias="редагування" controller="Edit" />
    </branch>
    <branch title="Категорії" alias="категорії" controller="Category">
        <branch title="Список" alias="список" controller="Index" menu="Категорії">
            <submenu>
                <item title="Створити" alias="редагування" />
                <item title="Фільтр" alias="фільтр" />
            </submenu>
        </branch>
        <branch title="Перегляд" alias="перегляд" controller="View" />
        <branch title="Редагування" alias="редагування" controller="Edit" />
    </branch>
    <branch title="Мітки" alias="мітки" controller="Tag">
        <branch title="Список" alias="список" controller="Index" menu="Мітки">
            <submenu>
                <item title="Створити" alias="редагування" />
                <item title="Фільтр" alias="фільтр" />
            </submenu>
        </branch>
        <branch title="Перегляд" alias="перегляд" controller="View" />
        <branch title="Редагування" alias="редагування" controller="Edit" />
    </branch>
    <branch title="Коментарі" alias="коментарі" controller="Comment">
        <branch title="Список" alias="список" controller="Index" menu="Коментарі">
            <submenu>
                <item title="Видалити" alias="редагування" />
                <item title="Фільтр" alias="фільтр" />
            </submenu>
        </branch>
        <branch title="Перегляд" alias="перегляд" controller="View" />
        <branch title="Редагування" alias="редагування" controller="Edit" />
    </branch>
    <branch title="Сторінки" alias="сторінки" controller="Page">
        <branch title="Список" alias="список" controller="Index" menu="Сторінки">
            <submenu>
                <item title="Створити" alias="редагування" />
                <item title="Фільтр" alias="фільтр" modal="#filter" />
            </submenu>
        </branch>
        <branch title="Редагування" alias="редагування" controller="Edit">
            <submenu>
                <item title="Закрити" alias="список" />
            </submenu>
        </branch>
    </branch>
    <branch title="Користувачі" alias="користувачі" controller="User">
        <branch title="Список" alias="список" controller="Index" menu="Користувачі">
            <submenu>
                <item title="Створити" alias="редагування" />
                <item title="Фільтр" alias="фільтр" modal="#filter" />
            </submenu>
        </branch>
        <branch title="Редагування" alias="редагування" controller="Edit">
            <submenu>
                <item title="Закрити" alias="список" />
            </submenu>
        </branch>
    </branch>
    <branch title="Доступ" alias="доступ" controller="Access">
        <branch title="Вхід" alias="вхід" controller="Login" />
        <branch title="Вихід" alias="вихід" controller="Logout" menu="Вихід" />
    </branch>
</tree>

