{
  "Article":        {"title": "Статті",         "alias": "статті", "actions": {
    "Index":        {"title": "Список",         "alias": "список"},
    "Edit":         {"title": "Редагування",    "alias": "редагування"}
  }},
  "Category":       {"title": "Категорії",      "alias": "категорії", "actions": {
    "Index":        {"title": "Список",         "alias": "список"},
    "Edit":         {"title": "Редагування",    "alias": "редагування"}
  }},
  "Tag":            {"title": "Мітки",          "alias": "мітки", "actions": {
    "Index":        {"title": "Список",         "alias": "список"},
    "Edit":         {"title": "Редагування",    "alias": "редагування"},
    "Autocomplete": {"title": "Автозаповнення", "alias": "автозаповнення", "isView": false}
  }},
  "Comment":        {"title": "Коментарі",      "alias": "коментарі", "actions": {
    "Index":        {"title": "Список",         "alias": "список"},
    "Edit":         {"title": "Редагування",    "alias": "редагування"}
  }},
  "Page":           {"title": "Сторінки",       "alias": "сторінки", "actions": {
    "Index":        {"title": "Список",         "alias": "список"},
    "Edit":         {"title": "Редагування",    "alias": "редагування"}
  }},
  "User":           {"title": "Користувачі",    "alias": "користувачі", "actions": {
    "Index":        {"title": "Список",         "alias": "список"},
    "Edit":         {"title": "Редагування",    "alias": "редагування"},
    "Login":        {"title": "Вхід",           "alias": "вхід"},
    "Logout":       {"title": "Вихід",          "alias": "вихід"}}
  }
}